{"meta_data":{"additional_headers":{},"game_name":"Recollect","version":"2.53.01","user_name":"121","organization":"braingamecenter","study":"mpl2_2022_11","session_number":0,"device_id":"74342D95-EE82-45E3-8ADF-48FB3203C5DD"},"data":[{"Event":"Start","stimSet":"DogsAndMonkeys","Time":1689983619805.17},{"Event":"Trial","state_name":"Mixed Assessment","row":0,"last_interacted_character":7,"hits":3,"misses":0,"false_alarms":2,"correct_rejections":3,"stim_sequence":"37105460","target_sequence":"00110001","responses":"10111001","hit_accuracy":0.6,"trial_start_time":1689983927560.92,"trial_end_time":1689983932909.46,"processing_time":5348.54296875},{"Event":"Trial","state_name":"Mixed Assessment","row":1,"last_interacted_character":6,"hits":4,"misses":1,"false_alarms":0,"correct_rejections":3,"stim_sequence":"61700710","target_sequence":"01011011","responses":"01011010","hit_accuracy":0.8,"trial_start_time":1689983933922.08,"trial_end_time":1689983939922.08,"processing_time":6000},{"Event":"Trial","state_name":"Mixed Assessment","row":2,"last_interacted_character":7,"hits":5,"misses":0,"false_alarms":0,"correct_rejections":3,"stim_sequence":"50021510","target_sequence":"01101011","responses":"01101011","hit_accuracy":1,"trial_start_time":1689983940940.11,"trial_end_time":1689983944689.22,"processing_time":3749.11254882813},{"Event":"Trial","state_name":"Mixed Assessment","row":3,"last_interacted_character":3,"hits":3,"misses":0,"false_alarms":0,"correct_rejections":5,"stim_sequence":"01703624","target_sequence":"11010000","responses":"11010000","hit_accuracy":1,"trial_start_time":1689983945705.77,"trial_end_time":1689983949221.35,"processing_time":3515.57202148438},{"Event":"Trial","state_name":"Mixed Assessment","row":4,"last_interacted_character":7,"hits":5,"misses":0,"false_alarms":0,"correct_rejections":3,"stim_sequence":"10550311","target_sequence":"11001011","responses":"11001011","hit_accuracy":1,"trial_start_time":1689983950236.37,"trial_end_time":1689983954968.79,"processing_time":4732.4169921875},{"Event":"Trial","state_name":"Mixed Assessment","row":5,"last_interacted_character":7,"hits":3,"misses":0,"false_alarms":0,"correct_rejections":5,"stim_sequence":"02077641","target_sequence":"10100001","responses":"10100001","hit_accuracy":1,"trial_start_time":1689983955985.07,"trial_end_time":1689983961550.61,"processing_time":5565.541015625},{"Event":"Trial","state_name":"Mixed Assessment","row":6,"last_interacted_character":7,"hits":5,"misses":0,"false_alarms":0,"correct_rejections":3,"stim_sequence":"03104601","target_sequence":"10110011","responses":"10110011","hit_accuracy":1,"trial_start_time":1689983962566.87,"trial_end_time":1689983966465.57,"processing_time":3898.705078125},{"Event":"Trial","state_name":"Mixed Assessment","row":7,"last_interacted_character":4,"hits":3,"misses":0,"false_alarms":0,"correct_rejections":5,"stim_sequence":"50301457","target_sequence":"01011000","responses":"01011000","hit_accuracy":1,"trial_start_time":1689983967481.71,"trial_end_time":1689983972130.17,"processing_time":4648.46142578125},{"Event":"Trial","state_name":"Mixed Assessment","row":8,"last_interacted_character":7,"hits":3,"misses":0,"false_alarms":0,"correct_rejections":5,"stim_sequence":"20375120","target_sequence":"01000101","responses":"01000101","hit_accuracy":1,"trial_start_time":1689983973147.22,"trial_end_time":1689983976962.6,"processing_time":3815.38354492188},{"Event":"Trial","state_name":"Mixed Assessment","row":9,"last_interacted_character":6,"hits":5,"misses":0,"false_alarms":0,"correct_rejections":3,"stim_sequence":"10206013","target_sequence":"11010110","responses":"11010110","hit_accuracy":1,"trial_start_time":1689983977977.55,"trial_end_time":1689983983543.13,"processing_time":5565.58203125},{"Event":"Trial","state_name":"Mixed Assessment","row":10,"last_interacted_character":7,"hits":5,"misses":0,"false_alarms":0,"correct_rejections":3,"stim_sequence":"05104410","target_sequence":"10110011","responses":"10110011","hit_accuracy":1,"trial_start_time":1689983984559.53,"trial_end_time":1689983988842.02,"processing_time":4282.48388671875},{"Event":"Trial","state_name":"Mixed Assessment","row":11,"last_interacted_character":7,"hits":3,"misses":0,"false_alarms":0,"correct_rejections":5,"stim_sequence":"37106570","target_sequence":"00110001","responses":"00110001","hit_accuracy":1,"trial_start_time":1689983989857.5,"trial_end_time":1689983993706.53,"processing_time":3849.02880859375},{"Event":"Trial","state_name":"Mixed Assessment","row":12,"last_interacted_character":7,"hits":5,"misses":0,"false_alarms":0,"correct_rejections":3,"stim_sequence":"17014150","target_sequence":"10110101","responses":"10110101","hit_accuracy":1,"trial_start_time":1689983994723.47,"trial_end_time":1689983999272.3,"processing_time":4548.83203125},{"Event":"Trial","state_name":"Mixed Assessment","row":13,"last_interacted_character":6,"hits":3,"misses":0,"false_alarms":0,"correct_rejections":5,"stim_sequence":"75604102","target_sequence":"00010110","responses":"00010110","hit_accuracy":1,"trial_start_time":1689984000287.64,"trial_end_time":1689984005169.92,"processing_time":4882.2724609375},{"Event":"Trial","state_name":"Mixed Assessment","row":14,"last_interacted_character":7,"hits":2,"misses":1,"false_alarms":0,"correct_rejections":5,"stim_sequence":"31731640","target_sequence":"01001001","responses":"01000001","hit_accuracy":0.6666667,"trial_start_time":1689984006184.96,"trial_end_time":1689984010366.9,"processing_time":4181.93994140625},{"Event":"Trial","state_name":"Mixed Assessment","row":15,"last_interacted_character":6,"hits":5,"misses":0,"false_alarms":0,"correct_rejections":3,"stim_sequence":"00612015","target_sequence":"11010110","responses":"11010110","hit_accuracy":1,"trial_start_time":1689984011384.08,"trial_end_time":1689984014850.02,"processing_time":3465.93603515625},{"Event":"Trial","state_name":"Mixed Assessment","row":16,"last_interacted_character":7,"hits":5,"misses":0,"false_alarms":0,"correct_rejections":3,"stim_sequence":"00721120","target_sequence":"11001101","responses":"11001101","hit_accuracy":1,"trial_start_time":1689984015865.67,"trial_end_time":1689984019864.33,"processing_time":3998.66162109375},{"Event":"Trial","state_name":"Mixed Assessment","row":17,"last_interacted_character":4,"hits":4,"misses":1,"false_alarms":0,"correct_rejections":3,"stim_sequence":"00511241","target_sequence":"11011001","responses":"11011000","hit_accuracy":0.8,"trial_start_time":1689984020880.78,"trial_end_time":1689984024546.7,"processing_time":3665.921875},{"Event":"Trial","state_name":"Mixed Assessment","row":18,"last_interacted_character":7,"hits":3,"misses":0,"false_alarms":0,"correct_rejections":5,"stim_sequence":"37621410","target_sequence":"00001011","responses":"00001011","hit_accuracy":1,"trial_start_time":1689984025562.26,"trial_end_time":1689984030977.16,"processing_time":5414.89697265625},{"Event":"Trial","state_name":"Mixed Assessment","row":19,"last_interacted_character":5,"hits":3,"misses":0,"false_alarms":0,"correct_rejections":5,"stim_sequence":"00624074","target_sequence":"11000100","responses":"11000100","hit_accuracy":1,"trial_start_time":1689984031993.76,"trial_end_time":1689984035859.08,"processing_time":3865.31909179688},{"Event":"Trial","state_name":"Mixed Assessment","row":20,"last_interacted_character":7,"hits":3,"misses":0,"false_alarms":0,"correct_rejections":5,"stim_sequence":"14320430","target_sequence":"10001001","responses":"10001001","hit_accuracy":1,"trial_start_time":1689984036871.95,"trial_end_time":1689984042871.95,"processing_time":6000},{"Event":"Trial","state_name":"Mixed Assessment","row":21,"last_interacted_character":7,"hits":5,"misses":0,"false_alarms":0,"correct_rejections":3,"stim_sequence":"01451600","target_sequence":"11001011","responses":"11001011","hit_accuracy":1,"trial_start_time":1689984043889.64,"trial_end_time":1689984047221.93,"processing_time":3332.28686523438},{"Event":"Trial","state_name":"Mixed Assessment","row":22,"last_interacted_character":7,"hits":3,"misses":0,"false_alarms":0,"correct_rejections":5,"stim_sequence":"16125251","target_sequence":"10100001","responses":"10100001","hit_accuracy":1,"trial_start_time":1689984048238.75,"trial_end_time":1689984052453.95,"processing_time":4215.20166015625},{"Event":"Trial","state_name":"Mixed Assessment","row":23,"last_interacted_character":7,"hits":4,"misses":0,"false_alarms":1,"correct_rejections":3,"stim_sequence":"13054611","target_sequence":"10100011","responses":"11100011","hit_accuracy":0.8,"trial_start_time":1689984053470.12,"trial_end_time":1689984058185.24,"processing_time":4715.1201171875},{"Event":"Trial","state_name":"Mixed Assessment","row":24,"last_interacted_character":7,"hits":3,"misses":2,"false_alarms":0,"correct_rejections":3,"stim_sequence":"20171700","target_sequence":"01101011","responses":"01000011","hit_accuracy":0.6,"trial_start_time":1689984059201.15,"trial_end_time":1689984063716.3,"processing_time":4515.1533203125},{"Event":"Trial","state_name":"Mixed Assessment","row":25,"last_interacted_character":5,"hits":4,"misses":0,"false_alarms":0,"correct_rejections":4,"stim_sequence":"10231177","target_sequence":"11001100","responses":"11001100","hit_accuracy":1,"trial_start_time":1689984064733.21,"trial_end_time":1689984067948.79,"processing_time":3215.58325195313},{"Event":"Trial","state_name":"Mixed Assessment","row":26,"last_interacted_character":5,"hits":4,"misses":1,"false_alarms":0,"correct_rejections":3,"stim_sequence":"13116070","target_sequence":"10110101","responses":"10110100","hit_accuracy":0.8,"trial_start_time":1689984068964.98,"trial_end_time":1689984072097.21,"processing_time":3132.23095703125},{"Event":"Trial","state_name":"Mixed Assessment","row":27,"last_interacted_character":7,"hits":3,"misses":0,"false_alarms":0,"correct_rejections":5,"stim_sequence":"24160551","target_sequence":"00101001","responses":"00101001","hit_accuracy":1,"trial_start_time":1689984073113.64,"trial_end_time":1689984076162.55,"processing_time":3048.91088867188},{"Event":"Trial","state_name":"Mixed Assessment","row":28,"last_interacted_character":7,"hits":5,"misses":0,"false_alarms":0,"correct_rejections":3,"stim_sequence":"11500250","target_sequence":"11011001","responses":"11011001","hit_accuracy":1,"trial_start_time":1689984077178.86,"trial_end_time":1689984080361.12,"processing_time":3182.26611328125},{"Event":"Trial","state_name":"Mixed Assessment","row":29,"last_interacted_character":5,"hits":3,"misses":0,"false_alarms":0,"correct_rejections":5,"stim_sequence":"32151072","target_sequence":"00101100","responses":"00101100","hit_accuracy":1,"trial_start_time":1689984081378.15,"trial_end_time":1689984085143.59,"processing_time":3765.43774414063},{"Event":"Trial","state_name":"Mixed Assessment","row":30,"last_interacted_character":6,"hits":4,"misses":0,"false_alarms":0,"correct_rejections":4,"stim_sequence":"60411712","target_sequence":"01011010","responses":"01011010","hit_accuracy":1,"trial_start_time":1689984086159.32,"trial_end_time":1689984089141.59,"processing_time":2982.263671875},{"Event":"Trial","state_name":"Mixed Assessment","row":31,"last_interacted_character":7,"hits":4,"misses":0,"false_alarms":0,"correct_rejections":4,"stim_sequence":"07715610","target_sequence":"10010011","responses":"10010011","hit_accuracy":1,"trial_start_time":1689984090158.07,"trial_end_time":1689984094457.05,"processing_time":4298.986328125},{"Event":"Trial","state_name":"Mixed Assessment","row":32,"last_interacted_character":6,"hits":4,"misses":0,"false_alarms":0,"correct_rejections":4,"stim_sequence":"00527016","target_sequence":"11000110","responses":"11000110","hit_accuracy":1,"trial_start_time":1689984095473.78,"trial_end_time":1689984098855.93,"processing_time":3382.1474609375},{"Event":"Trial","state_name":"Mixed Assessment","row":33,"last_interacted_character":7,"hits":5,"misses":0,"false_alarms":0,"correct_rejections":3,"stim_sequence":"11440201","target_sequence":"11001011","responses":"11001011","hit_accuracy":1,"trial_start_time":1689984099871.85,"trial_end_time":1689984102887.42,"processing_time":3015.57763671875},{"Event":"Trial","state_name":"Mixed Assessment","row":34,"last_interacted_character":5,"hits":4,"misses":0,"false_alarms":0,"correct_rejections":4,"stim_sequence":"11520067","target_sequence":"11001100","responses":"11001100","hit_accuracy":1,"trial_start_time":1689984103904.17,"trial_end_time":1689984108619.21,"processing_time":4715.03662109375},{"Event":"Trial","state_name":"Mixed Assessment","row":35,"last_interacted_character":4,"hits":3,"misses":0,"false_alarms":0,"correct_rejections":5,"stim_sequence":"20060477","target_sequence":"01101000","responses":"01101000","hit_accuracy":1,"trial_start_time":1689984109635.83,"trial_end_time":1689984113267.9,"processing_time":3632.07299804688},{"Event":"Trial","state_name":"Mixed Assessment","row":36,"last_interacted_character":7,"hits":5,"misses":0,"false_alarms":0,"correct_rejections":3,"stim_sequence":"30401710","target_sequence":"01011011","responses":"01011011","hit_accuracy":1,"trial_start_time":1689984114283.31,"trial_end_time":1689984118282.09,"processing_time":3998.77221679688},{"Event":"Trial","state_name":"Mixed Assessment","row":37,"last_interacted_character":6,"hits":5,"misses":0,"false_alarms":0,"correct_rejections":3,"stim_sequence":"00517112","target_sequence":"11010110","responses":"11010110","hit_accuracy":1,"trial_start_time":1689984119298.15,"trial_end_time":1689984124763.72,"processing_time":5465.57861328125},{"Event":"Trial","state_name":"Mixed Assessment","row":38,"last_interacted_character":7,"hits":3,"misses":0,"false_alarms":0,"correct_rejections":5,"stim_sequence":"00672371","target_sequence":"11000001","responses":"11000001","hit_accuracy":1,"trial_start_time":1689984125779.88,"trial_end_time":1689984129312.49,"processing_time":3532.61059570313},{"Event":"Trial","state_name":"Mixed Assessment","row":39,"last_interacted_character":5,"hits":3,"misses":0,"false_alarms":1,"correct_rejections":4,"stim_sequence":"31640155","target_sequence":"01001100","responses":"11001100","hit_accuracy":0.75,"trial_start_time":1689984130328.18,"trial_end_time":1689984134544.05,"processing_time":4215.86328125},{"Event":"Trial","state_name":"Mixed Assessment","row":40,"last_interacted_character":7,"hits":2,"misses":1,"false_alarms":0,"correct_rejections":5,"stim_sequence":"16352710","target_sequence":"10000011","responses":"10000001","hit_accuracy":0.6666667,"trial_start_time":1689984135559.87,"trial_end_time":1689984141424.91,"processing_time":5865.0419921875},{"Event":"End","Time":1689984144058.57}]}