{"meta_data":{"additional_headers":{},"game_name":"Recollect","version":"2.53.01","user_name":"61","organization":"braingamecenter","study":"mpl2_2022_11","session_number":0,"device_id":"74342D95-EE82-45E3-8ADF-48FB3203C5DD"},"data":[{"Event":"Start","stimSet":"DogsAndMonkeys","Time":1678997904102.36},{"Event":"Trial","state_name":"Mixed Assessment","row":0,"last_interacted_character":7,"hits":3,"misses":0,"false_alarms":0,"correct_rejections":5,"stim_sequence":"24006271","target_sequence":"00110001","responses":"00110001","hit_accuracy":1,"trial_start_time":1678998241027.05,"trial_end_time":1678998244509.16,"processing_time":3482.10986328125},{"Event":"Trial","state_name":"Mixed Assessment","row":1,"last_interacted_character":5,"hits":4,"misses":0,"false_alarms":0,"correct_rejections":4,"stim_sequence":"04031074","target_sequence":"10101100","responses":"10101100","hit_accuracy":1,"trial_start_time":1678998245525.08,"trial_end_time":1678998249340.52,"processing_time":3815.43432617188},{"Event":"Trial","state_name":"Mixed Assessment","row":2,"last_interacted_character":6,"hits":4,"misses":0,"false_alarms":0,"correct_rejections":4,"stim_sequence":"01570612","target_sequence":"11001010","responses":"11001010","hit_accuracy":1,"trial_start_time":1678998250357.64,"trial_end_time":1678998254256.32,"processing_time":3898.6748046875},{"Event":"Trial","state_name":"Mixed Assessment","row":3,"last_interacted_character":7,"hits":5,"misses":0,"false_alarms":0,"correct_rejections":3,"stim_sequence":"06120501","target_sequence":"10101011","responses":"10101011","hit_accuracy":1,"trial_start_time":1678998255271.69,"trial_end_time":1678998259087.11,"processing_time":3815.42700195313},{"Event":"Trial","state_name":"Mixed Assessment","row":4,"last_interacted_character":4,"hits":4,"misses":0,"false_alarms":0,"correct_rejections":4,"stim_sequence":"10211674","target_sequence":"11011000","responses":"11011000","hit_accuracy":1,"trial_start_time":1678998260103.79,"trial_end_time":1678998265152.09,"processing_time":5048.30419921875},{"Event":"Trial","state_name":"Mixed Assessment","row":5,"last_interacted_character":7,"hits":4,"misses":0,"false_alarms":0,"correct_rejections":4,"stim_sequence":"07137071","target_sequence":"10100101","responses":"10100101","hit_accuracy":1,"trial_start_time":1678998266168.79,"trial_end_time":1678998269550.99,"processing_time":3382.1943359375},{"Event":"Trial","state_name":"Mixed Assessment","row":6,"last_interacted_character":6,"hits":4,"misses":0,"false_alarms":0,"correct_rejections":4,"stim_sequence":"61056015","target_sequence":"01100110","responses":"01100110","hit_accuracy":1,"trial_start_time":1678998270567.24,"trial_end_time":1678998274649.25,"processing_time":4082.00463867188},{"Event":"Trial","state_name":"Mixed Assessment","row":7,"last_interacted_character":5,"hits":4,"misses":0,"false_alarms":0,"correct_rejections":4,"stim_sequence":"05115044","target_sequence":"10110100","responses":"10110100","hit_accuracy":1,"trial_start_time":1678998275665.61,"trial_end_time":1678998278697.93,"processing_time":3032.31372070313},{"Event":"Trial","state_name":"Mixed Assessment","row":8,"last_interacted_character":7,"hits":4,"misses":0,"false_alarms":0,"correct_rejections":4,"stim_sequence":"03604170","target_sequence":"10010101","responses":"10010101","hit_accuracy":1,"trial_start_time":1678998279714.01,"trial_end_time":1678998283479.46,"processing_time":3765.44702148438},{"Event":"Trial","state_name":"Mixed Assessment","row":9,"last_interacted_character":7,"hits":4,"misses":0,"false_alarms":0,"correct_rejections":4,"stim_sequence":"51130750","target_sequence":"01101001","responses":"01101001","hit_accuracy":1,"trial_start_time":1678998284495.43,"trial_end_time":1678998288427.45,"processing_time":3932.0263671875},{"Event":"Trial","state_name":"Mixed Assessment","row":10,"last_interacted_character":6,"hits":3,"misses":0,"false_alarms":0,"correct_rejections":5,"stim_sequence":"15441412","target_sequence":"10001010","responses":"10001010","hit_accuracy":1,"trial_start_time":1678998289444.49,"trial_end_time":1678998293143.26,"processing_time":3698.7705078125},{"Event":"Trial","state_name":"Mixed Assessment","row":11,"last_interacted_character":7,"hits":5,"misses":0,"false_alarms":0,"correct_rejections":3,"stim_sequence":"03016401","target_sequence":"10110011","responses":"10110011","hit_accuracy":1,"trial_start_time":1678998294159.29,"trial_end_time":1678998297941.36,"processing_time":3782.0673828125},{"Event":"Trial","state_name":"Mixed Assessment","row":12,"last_interacted_character":7,"hits":3,"misses":0,"false_alarms":0,"correct_rejections":5,"stim_sequence":"36705051","target_sequence":"00010101","responses":"00010101","hit_accuracy":1,"trial_start_time":1678998298957.83,"trial_end_time":1678998303306.37,"processing_time":4348.533203125},{"Event":"Trial","state_name":"Mixed Assessment","row":13,"last_interacted_character":6,"hits":3,"misses":0,"false_alarms":0,"correct_rejections":5,"stim_sequence":"47016702","target_sequence":"00110010","responses":"00110010","hit_accuracy":1,"trial_start_time":1678998304322.59,"trial_end_time":1678998309104.31,"processing_time":4781.7197265625},{"Event":"Trial","state_name":"Mixed Assessment","row":14,"last_interacted_character":6,"hits":4,"misses":1,"false_alarms":0,"correct_rejections":3,"stim_sequence":"05121401","target_sequence":"10101011","responses":"10101010","hit_accuracy":0.8,"trial_start_time":1678998310121.2,"trial_end_time":1678998313886.56,"processing_time":3765.35546875},{"Event":"Trial","state_name":"Mixed Assessment","row":15,"last_interacted_character":5,"hits":4,"misses":0,"false_alarms":0,"correct_rejections":4,"stim_sequence":"60041125","target_sequence":"01101100","responses":"01101100","hit_accuracy":1,"trial_start_time":1678998314902.98,"trial_end_time":1678998320201.12,"processing_time":5298.13671875},{"Event":"Trial","state_name":"Mixed Assessment","row":16,"last_interacted_character":7,"hits":5,"misses":0,"false_alarms":0,"correct_rejections":3,"stim_sequence":"11671070","target_sequence":"11001101","responses":"11001101","hit_accuracy":1,"trial_start_time":1678998321217.29,"trial_end_time":1678998326698.77,"processing_time":5481.4755859375},{"Event":"Trial","state_name":"Mixed Assessment","row":17,"last_interacted_character":7,"hits":5,"misses":0,"false_alarms":0,"correct_rejections":3,"stim_sequence":"04401211","target_sequence":"10011011","responses":"10011011","hit_accuracy":1,"trial_start_time":1678998327715.09,"trial_end_time":1678998332646.76,"processing_time":4931.669921875},{"Event":"Trial","state_name":"Mixed Assessment","row":18,"last_interacted_character":7,"hits":3,"misses":0,"false_alarms":1,"correct_rejections":4,"stim_sequence":"31051573","target_sequence":"01101000","responses":"01101001","hit_accuracy":0.75,"trial_start_time":1678998333663.39,"trial_end_time":1678998338894.9,"processing_time":5231.50634765625},{"Event":"Trial","state_name":"Mixed Assessment","row":19,"last_interacted_character":6,"hits":4,"misses":0,"false_alarms":0,"correct_rejections":4,"stim_sequence":"15161305","target_sequence":"10101010","responses":"10101010","hit_accuracy":1,"trial_start_time":1678998339908.09,"trial_end_time":1678998343843.16,"processing_time":3935.07006835938},{"Event":"Trial","state_name":"Mixed Assessment","row":20,"last_interacted_character":7,"hits":4,"misses":0,"false_alarms":0,"correct_rejections":4,"stim_sequence":"13176040","target_sequence":"10100101","responses":"10100101","hit_accuracy":1,"trial_start_time":1678998344859.54,"trial_end_time":1678998349124.78,"processing_time":4265.23486328125},{"Event":"Trial","state_name":"Mixed Assessment","row":21,"last_interacted_character":7,"hits":4,"misses":0,"false_alarms":0,"correct_rejections":4,"stim_sequence":"14704130","target_sequence":"10010101","responses":"10010101","hit_accuracy":1,"trial_start_time":1678998350141.22,"trial_end_time":1678998353723.3,"processing_time":3582.0869140625},{"Event":"Trial","state_name":"Mixed Assessment","row":22,"last_interacted_character":7,"hits":4,"misses":0,"false_alarms":0,"correct_rejections":4,"stim_sequence":"14310540","target_sequence":"10011001","responses":"10011001","hit_accuracy":1,"trial_start_time":1678998354740.55,"trial_end_time":1678998358172.65,"processing_time":3432.1044921875},{"Event":"Trial","state_name":"Mixed Assessment","row":23,"last_interacted_character":7,"hits":4,"misses":1,"false_alarms":0,"correct_rejections":3,"stim_sequence":"11541600","target_sequence":"11001011","responses":"11000011","hit_accuracy":0.8,"trial_start_time":1678998359184.84,"trial_end_time":1678998365184.84,"processing_time":6000},{"Event":"Trial","state_name":"Mixed Assessment","row":24,"last_interacted_character":4,"hits":3,"misses":0,"false_alarms":0,"correct_rejections":5,"stim_sequence":"31700225","target_sequence":"01011000","responses":"01011000","hit_accuracy":1,"trial_start_time":1678998366203.34,"trial_end_time":1678998370751.81,"processing_time":4548.46728515625},{"Event":"Trial","state_name":"Mixed Assessment","row":25,"last_interacted_character":7,"hits":4,"misses":0,"false_alarms":0,"correct_rejections":4,"stim_sequence":"66004131","target_sequence":"00110101","responses":"00110101","hit_accuracy":1,"trial_start_time":1678998371768.28,"trial_end_time":1678998376033.46,"processing_time":4265.1806640625},{"Event":"Trial","state_name":"Mixed Assessment","row":26,"last_interacted_character":7,"hits":4,"misses":0,"false_alarms":0,"correct_rejections":4,"stim_sequence":"02151540","target_sequence":"10101001","responses":"10101001","hit_accuracy":1,"trial_start_time":1678998377048.86,"trial_end_time":1678998380247.76,"processing_time":3198.89916992188},{"Event":"Trial","state_name":"Mixed Assessment","row":27,"last_interacted_character":7,"hits":4,"misses":0,"false_alarms":0,"correct_rejections":4,"stim_sequence":"05350210","target_sequence":"10001011","responses":"10001011","hit_accuracy":1,"trial_start_time":1678998381264.31,"trial_end_time":1678998385046.41,"processing_time":3782.10205078125},{"Event":"Trial","state_name":"Mixed Assessment","row":28,"last_interacted_character":7,"hits":4,"misses":0,"false_alarms":0,"correct_rejections":4,"stim_sequence":"44700401","target_sequence":"00011011","responses":"00011011","hit_accuracy":1,"trial_start_time":1678998386062.96,"trial_end_time":1678998390044.97,"processing_time":3982.00268554688},{"Event":"Trial","state_name":"Mixed Assessment","row":29,"last_interacted_character":7,"hits":4,"misses":0,"false_alarms":0,"correct_rejections":4,"stim_sequence":"01626140","target_sequence":"11000101","responses":"11000101","hit_accuracy":1,"trial_start_time":1678998391061.53,"trial_end_time":1678998394460.38,"processing_time":3398.8515625},{"Event":"Trial","state_name":"Mixed Assessment","row":30,"last_interacted_character":7,"hits":3,"misses":0,"false_alarms":0,"correct_rejections":5,"stim_sequence":"37067120","target_sequence":"00100101","responses":"00100101","hit_accuracy":1,"trial_start_time":1678998395476.79,"trial_end_time":1678998399558.72,"processing_time":4081.93212890625},{"Event":"Trial","state_name":"Mixed Assessment","row":31,"last_interacted_character":7,"hits":4,"misses":0,"false_alarms":0,"correct_rejections":4,"stim_sequence":"66115410","target_sequence":"00110011","responses":"00110011","hit_accuracy":1,"trial_start_time":1678998400574.23,"trial_end_time":1678998403823.09,"processing_time":3248.86010742188},{"Event":"Trial","state_name":"Mixed Assessment","row":32,"last_interacted_character":7,"hits":4,"misses":0,"false_alarms":0,"correct_rejections":4,"stim_sequence":"05107330","target_sequence":"10110001","responses":"10110001","hit_accuracy":1,"trial_start_time":1678998404840.35,"trial_end_time":1678998409505.44,"processing_time":4665.09130859375},{"Event":"Trial","state_name":"Mixed Assessment","row":33,"last_interacted_character":7,"hits":4,"misses":0,"false_alarms":0,"correct_rejections":4,"stim_sequence":"00347511","target_sequence":"11000011","responses":"11000011","hit_accuracy":1,"trial_start_time":1678998410521.91,"trial_end_time":1678998414004.12,"processing_time":3482.205078125},{"Event":"Trial","state_name":"Mixed Assessment","row":34,"last_interacted_character":7,"hits":4,"misses":0,"false_alarms":0,"correct_rejections":4,"stim_sequence":"27003021","target_sequence":"00110101","responses":"00110101","hit_accuracy":1,"trial_start_time":1678998415020.29,"trial_end_time":1678998418669.07,"processing_time":3648.7783203125},{"Event":"Trial","state_name":"Mixed Assessment","row":35,"last_interacted_character":7,"hits":4,"misses":0,"false_alarms":0,"correct_rejections":4,"stim_sequence":"60715210","target_sequence":"01010011","responses":"01010011","hit_accuracy":1,"trial_start_time":1678998419685.42,"trial_end_time":1678998423500.8,"processing_time":3815.37963867188},{"Event":"Trial","state_name":"Mixed Assessment","row":36,"last_interacted_character":4,"hits":4,"misses":0,"false_alarms":0,"correct_rejections":4,"stim_sequence":"11400664","target_sequence":"11011000","responses":"11011000","hit_accuracy":1,"trial_start_time":1678998424516.96,"trial_end_time":1678998427832.53,"processing_time":3315.57543945313},{"Event":"Trial","state_name":"Mixed Assessment","row":37,"last_interacted_character":7,"hits":5,"misses":0,"false_alarms":0,"correct_rejections":3,"stim_sequence":"11507020","target_sequence":"11010101","responses":"11010101","hit_accuracy":1,"trial_start_time":1678998428849.4,"trial_end_time":1678998432631.46,"processing_time":3782.05981445313},{"Event":"Trial","state_name":"Mixed Assessment","row":38,"last_interacted_character":6,"hits":4,"misses":0,"false_alarms":0,"correct_rejections":4,"stim_sequence":"07400612","target_sequence":"10011010","responses":"10011010","hit_accuracy":1,"trial_start_time":1678998433647.43,"trial_end_time":1678998437646.08,"processing_time":3998.64916992188},{"Event":"Trial","state_name":"Mixed Assessment","row":39,"last_interacted_character":5,"hits":4,"misses":0,"false_alarms":0,"correct_rejections":4,"stim_sequence":"02104047","target_sequence":"10110100","responses":"10110100","hit_accuracy":1,"trial_start_time":1678998438661.76,"trial_end_time":1678998442843.66,"processing_time":4181.89599609375},{"Event":"Trial","state_name":"Mixed Assessment","row":40,"last_interacted_character":7,"hits":4,"misses":0,"false_alarms":0,"correct_rejections":4,"stim_sequence":"70020631","target_sequence":"01101001","responses":"01101001","hit_accuracy":1,"trial_start_time":1678998443861.47,"trial_end_time":1678998447360.29,"processing_time":3498.82397460938},{"Event":"Trial","state_name":"Mixed Assessment","row":41,"last_interacted_character":7,"hits":4,"misses":0,"false_alarms":0,"correct_rejections":4,"stim_sequence":"01240371","target_sequence":"11001001","responses":"11001001","hit_accuracy":1,"trial_start_time":1678998448375.85,"trial_end_time":1678998452674.37,"processing_time":4298.51904296875},{"Event":"End","Time":1678998456873.77}]}